face_gest_loader/__init__.py
face_gest_loader/loader.py
face_gest_loader-0.1.dist-info/LICENSE
face_gest_loader-0.1.dist-info/METADATA
face_gest_loader-0.1.dist-info/WHEEL
face_gest_loader-0.1.dist-info/top_level.txt
face_gest_loader-0.1.dist-info/RECORD
