Metadata-Version: 2.1
Name: face-gest-loader
Version: 0.1
Summary: Loading FaceGest dataset
Home-page: https://github.com/yaseen21khan/FaceGest_Repo
Author: Yaseen/Sonain amil
Author-email: yaseen@sju.ac.kr
Classifier: Programming Language :: Python :: 3
Classifier: License :: OSI Approved :: MIT License
Classifier: Operating System :: OS Independent
Requires-Python: >=3.6
License-File: LICENSE
Requires-Dist: pandas
